setup.py
eh_probability/Binomialdistribution.py
eh_probability/Gaussiandistribution.py
eh_probability/Generaldistribution.py
eh_probability/__init__.py
eh_probability.egg-info/PKG-INFO
eh_probability.egg-info/SOURCES.txt
eh_probability.egg-info/dependency_links.txt
eh_probability.egg-info/not-zip-safe
eh_probability.egg-info/top_level.txt