Metadata-Version: 2.1
Name: eh-probability
Version: 0.1
Summary: Gaussian and binomoal distributions
Home-page: UNKNOWN
License: UNKNOWN
Platform: UNKNOWN
